aws_grobid/__init__.py
aws_grobid/core.py
aws_grobid/py.typed
aws_grobid/bin/__init__.py
aws_grobid/bin/cli.py
aws_grobid/static/nvidia-docker-install.sh
aws_grobid/static/startup-script.jinja
aws_grobid/static/ubuntu-amis.json
aws_grobid-0.2.0.dist-info/licenses/LICENSE
docs/AWS_PERMISSIONS.md
aws_grobid-0.2.0.dist-info/METADATA
aws_grobid-0.2.0.dist-info/WHEEL
aws_grobid-0.2.0.dist-info/entry_points.txt
aws_grobid-0.2.0.dist-info/top_level.txt
aws_grobid-0.2.0.dist-info/RECORD
