Metadata-Version: 2.4
Name: aws-grobid
Version: 0.2.0
Summary: Deploy GROBID on AWS EC2
Author-email: Eva Maxfield Brown <evamaxfieldbrown@gmail.com>
License: MIT License
Project-URL: Homepage, https://github.com/evamaxfield/aws-grobid
Project-URL: Bug Tracker, https://github.com/evamaxfield/aws-grobid/issues
Project-URL: Documentation, https://evamaxfield.github.io/aws-grobid
Project-URL: User Support, https://github.com/evamaxfield/aws-grobid/issues
Classifier: Development Status :: 4 - Beta
Classifier: Natural Language :: English
Classifier: Programming Language :: Python :: 3.11
Classifier: Programming Language :: Python :: 3.12
Classifier: Programming Language :: Python :: 3.13
Requires-Python: >=3.11
License-File: LICENSE
Requires-Dist: boto3<2,>=1
Requires-Dist: Jinja2<4,>=3
Requires-Dist: python-dotenv==1.0.1
Requires-Dist: requests<3,>=2
Provides-Extra: lint
Requires-Dist: pre-commit>=2.20.0; extra == "lint"
Provides-Extra: dev
Requires-Dist: ipython; extra == "dev"
Requires-Dist: jupyterlab; extra == "dev"
Requires-Dist: boto3-stubs[ec2]<2,>=1; extra == "dev"
Dynamic: license-file
